README.md
setup.cfg
setup.py
iomed/__init__.py
iomed/__main__.py
iomed/batch_parsing.py
iomed/logs.py
iomed/mel.py
iomed.egg-info/PKG-INFO
iomed.egg-info/SOURCES.txt
iomed.egg-info/dependency_links.txt
iomed.egg-info/entry_points.txt
iomed.egg-info/requires.txt
iomed.egg-info/top_level.txt