Metadata-Version: 1.0
Name: iomed
Version: 0.2.12
Summary: cli to IOMED Medical Language API
Home-page: https://github.com/iomedhealth/pyomed
Author: IOMED Medical Solutions SL
Author-email: dev@iomed.es
License: UNKNOWN
Platform: UNKNOWN
